hed_exceptions/__init__.py
hed_exceptions/exceptions.py
hed_exceptions/frames.py
hed_exceptions-0.0.4.dist-info/LICENSE.txt
hed_exceptions-0.0.4.dist-info/METADATA
hed_exceptions-0.0.4.dist-info/WHEEL
hed_exceptions-0.0.4.dist-info/top_level.txt
hed_exceptions-0.0.4.dist-info/RECORD
