Metadata-Version: 2.1
Name: hed-exceptions
Version: 0.0.4
Summary: Set of custom exceptions aimed to reduce typing.
Home-page: https://github.com/Hrissimir/hed_exceptions
Author: Hrissimir
Author-email: hrisimir.dakov@gmail.com
License: UNKNOWN
Platform: UNKNOWN
Classifier: Programming Language :: Python :: 3
Classifier: License :: OSI Approved :: MIT License
Classifier: Operating System :: OS Independent
Requires-Python: >=3.6
